WordBank/__init__.py
WordBank/main.py
WordBank-1.4.dist-info/METADATA
WordBank-1.4.dist-info/WHEEL
WordBank-1.4.dist-info/top_level.txt
WordBank-1.4.dist-info/RECORD
