Metadata-Version: 2.1
Name: WordBank
Version: 1.4
Requires-Dist: nltk
